dizegua/__init__.py
dizegua/diz_egua.py
dizegua-0.1.4.dist-info/METADATA
dizegua-0.1.4.dist-info/WHEEL
dizegua-0.1.4.dist-info/top_level.txt
dizegua-0.1.4.dist-info/RECORD
