Metadata-Version: 2.1
Name: dizegua
Version: 0.1.4
Summary: Esse pacote só diz égua
Author: Thalyson Wilker
Author-email: thalison.wilker@gmail.com
Keywords: python,first package
Classifier: Development Status :: 3 - Alpha
Classifier: Intended Audience :: Education
Classifier: Programming Language :: Python :: 2
Classifier: Programming Language :: Python :: 3
Classifier: Operating System :: MacOS :: MacOS X
Classifier: Operating System :: Microsoft :: Windows
